bpc/__init__.py
bpc/config.py
bpc/main.py
bpc/util.py
bpc/log/__init__.py
bpc/log/impl.py
black_pixel_convertor-0.0.2.dist-info/LICENSE
black_pixel_convertor-0.0.2.dist-info/METADATA
black_pixel_convertor-0.0.2.dist-info/WHEEL
black_pixel_convertor-0.0.2.dist-info/top_level.txt
black_pixel_convertor-0.0.2.dist-info/RECORD
