Metadata-Version: 2.1
Name: black-pixel-convertor
Version: 0.0.2
Summary: This library change black pixels to invisible.
Home-page: UNKNOWN
Author: 
Author-email: 
License: UNKNOWN
Platform: UNKNOWN
Classifier: Programming Language :: Python :: 3.11
Classifier: License :: OSI Approved :: MIT License
Requires-Dist: patchify
Requires-Dist: numpy
Requires-Dist: pillow
